<?xml version="1.0" encoding="UTF-8"?>
<directory>
    <roles>
        <name>ApprovalRole</name>
        <documentation>
            <localizedDocumentations>
                <locale>en_US</locale>
                <label>ApprovalRole</label>
            </localizedDocumentations>
            <localizedDocumentations>
                <locale>fr_FR</locale>
            </localizedDocumentations>
        </documentation>
    </roles>
    <roles>
        <name>ApprovalRole1</name>
        <documentation>
            <localizedDocumentations>
                <locale>en_US</locale>
            </localizedDocumentations>
            <localizedDocumentations>
                <locale>fr_FR</locale>
            </localizedDocumentations>
        </documentation>
    </roles>
    <roles>
        <name>Data Owner</name>
        <documentation>
            <localizedDocumentations>
                <locale>en_US</locale>
                <label>Data Owner</label>
            </localizedDocumentations>
            <localizedDocumentations>
                <locale>fr_FR</locale>
            </localizedDocumentations>
        </documentation>
    </roles>
    <roles>
        <name>Data Steward</name>
        <documentation>
            <localizedDocumentations>
                <locale>en_US</locale>
                <label>Data Steward</label>
            </localizedDocumentations>
            <localizedDocumentations>
                <locale>fr_FR</locale>
            </localizedDocumentations>
        </documentation>
    </roles>
    <roles>
        <name>DataOwner</name>
        <documentation>
            <localizedDocumentations>
                <locale>en_US</locale>
            </localizedDocumentations>
            <localizedDocumentations>
                <locale>fr_FR</locale>
            </localizedDocumentations>
        </documentation>
    </roles>
    <roles>
        <name>DataSteward</name>
        <documentation>
            <localizedDocumentations>
                <locale>en_US</locale>
            </localizedDocumentations>
            <localizedDocumentations>
                <locale>fr_FR</locale>
            </localizedDocumentations>
        </documentation>
    </roles>
    <roles>
        <name>Role1</name>
        <documentation>
            <localizedDocumentations>
                <locale>en_US</locale>
                <label>Role1</label>
            </localizedDocumentations>
            <localizedDocumentations>
                <locale>fr_FR</locale>
            </localizedDocumentations>
        </documentation>
    </roles>
    <roles>
        <name>Tech Admin</name>
        <documentation>
            <localizedDocumentations>
                <locale>en_US</locale>
            </localizedDocumentations>
            <localizedDocumentations>
                <locale>fr_FR</locale>
            </localizedDocumentations>
        </documentation>
    </roles>
</directory>
